{
  "project_info": {
    "project_number": "996543350810",
    "project_id": "media-survey",
    "storage_bucket": "media-survey.appspot.com"
  },
  "client": [
    {
      "client_info": {
        "mobilesdk_app_id": "1:996543350810:android:c5d4be0f26a45adf8d69a3",
        "android_client_info": {
          "package_name": "com.recoveryrecord.surveyandroid"
        }
      },
      "oauth_client": [
        {
          "client_id": "996543350810-dvl8guitnl4cqui43shtakhimcmi4dhs.apps.googleusercontent.com",
          "client_type": 3
        }
      ],
      "api_key": [
        {
          "current_key": "AIzaSyCZYT6wsVsR3216FuFoQHYWt4eiIDrEhWs"
        }
      ],
      "services": {
        "appinvite_service": {
          "other_platform_oauth_client": [
            {
              "client_id": "996543350810-dvl8guitnl4cqui43shtakhimcmi4dhs.apps.googleusercontent.com",
              "client_type": 3
            }
          ]
        }
      }
    }
  ],
  "configuration_version": "1"
}